winner/__init__.py
winner/cli/__init__.py
winner/cli/cli.py
winner/comm/__init__.py
winner/comm/acharya_train_eval_pb2.py
winner/comm/acharya_train_eval_pb2_grpc.py
winner/setup/__init__.py
winner/setup/__main__.py
winner/setup/initialize.py
winner/training/__init__.py
winner/training/sample_trainer.py
winner/training/train_eval.py
winner/training/yamlConfig.py
winner/utilities/__init__.py
winner/utilities/iob_split.py
winner/utils/__init__.py
winner/utils/iob_split.py
winner-0.0.1.1.dist-info/LICENSE
winner-0.0.1.1.dist-info/METADATA
winner-0.0.1.1.dist-info/WHEEL
winner-0.0.1.1.dist-info/top_level.txt
winner-0.0.1.1.dist-info/RECORD
